{
    "_ac": 3,
    "_alignmentsAllowed": [],
    "_article": "some",
    "_breakable": true,
    "_broken": false,
    "_carry": true,
    "_charges": 150,
    "_classesAllowed": [],
    "_cooldown": 0,
    "_cursed": false,
    "_depleatable": true,
    "_dodgeBonus": 0,
    "_enchanted": false,
    "_equippedSlotName": "",
    "_gendersAllowed": [],
    "_hasMetal": true,
    "_hidden": false,
    "_invisible": false,
    "_isObject": true,
    "_lastUse": null,
    "_longdesc": "a mixture of large metal sheets and chain mail fitted together to make a full shirt of metal to defend against the raging attacks of your enemies.",
    "_magic": false,
    "_maxCharges": 150,
    "_maxLevelAllowed": 100,
    "_minLevelAllowed": 0,
    "_name": "armor",
    "_permanent": false,
    "_pluraldesc": "pairs of half plate armor",
    "_singledesc": "half plate armor",
    "_timesRepaired": 0,
    "_value": 150,
    "_weight": 30,
    "objId": 150,
    "py/object": "object.Armor"
}