{
    "_antiMagic": false,
    "_dark": false,
    "_datafile": "",
    "_desc": "at the eastern end of Mountain Road, where the city wall curves to the north.  You feel like you are being watched.",
    "_encounterList": [],
    "_encounterRate": 0,
    "_inventoryTruncSize": 12,
    "_notifyDM": false,
    "_permanentList": [],
    "_priceBonus": 0,
    "_roomNum": 171,
    "_safe": false,
    "_shortDesc": "walking along the city wall on Mountain Road.",
    "d": 0,
    "e": 0,
    "n": 0,
    "o": 0,
    "py/object": "room.Room",
    "s": 0,
    "u": 0,
    "w": 172
}